gym_raas/__init__.py
gym_raas/envs/PendulumEnv.py
gym_raas/envs/__init__.py
gym_raas-0.0.1.dist-info/LICENSE
gym_raas-0.0.1.dist-info/METADATA
gym_raas-0.0.1.dist-info/WHEEL
gym_raas-0.0.1.dist-info/top_level.txt
gym_raas-0.0.1.dist-info/RECORD
